asr_enhancer/__init__.py
asr_enhancer/core.py
asr_enhancer/simple_pipeline.py
asr_enhancer/unified_pipeline.py
asr_enhancer/api/__init__.py
asr_enhancer/api/api_keys.py
asr_enhancer/api/enhance_endpoint.py
asr_enhancer/api/main.py
asr_enhancer/api/routes.py
asr_enhancer/api/schemas.py
asr_enhancer/cli/__init__.py
asr_enhancer/detectors/__init__.py
asr_enhancer/detectors/anomaly_detector.py
asr_enhancer/detectors/confidence_detector.py
asr_enhancer/detectors/gap_detector.py
asr_enhancer/detectors/numeric_gap_detector.py
asr_enhancer/detectors/smart_gap_detector.py
asr_enhancer/fusion/__init__.py
asr_enhancer/fusion/fusion_engine.py
asr_enhancer/fusion/scorers.py
asr_enhancer/fusion/selector.py
asr_enhancer/llm/__init__.py
asr_enhancer/llm/context_restorer.py
asr_enhancer/llm/local_llm.py
asr_enhancer/llm/prompt_templates.py
asr_enhancer/llm/providers.py
asr_enhancer/numeric/__init__.py
asr_enhancer/numeric/pattern_analyzer.py
asr_enhancer/numeric/sequence_reconstructor.py
asr_enhancer/numeric/validators.py
asr_enhancer/resynthesis/__init__.py
asr_enhancer/resynthesis/fast_asr.py
asr_enhancer/resynthesis/riva_backend.py
asr_enhancer/resynthesis/secondary_asr.py
asr_enhancer/resynthesis/segment_extractor.py
asr_enhancer/resynthesis/whisper_backend.py
asr_enhancer/utils/__init__.py
asr_enhancer/utils/audio.py
asr_enhancer/utils/config.py
asr_enhancer/utils/hindi_corrector.py
asr_enhancer/utils/logging.py
asr_enhancer/utils/text.py
asr_enhancer/validators/__init__.py
asr_enhancer/validators/completeness_validator.py
asr_enhancer/validators/consistency_checker.py
asr_enhancer/validators/perplexity_scorer.py
asr_enhancer/vocab/__init__.py
asr_enhancer/vocab/corrector.py
asr_enhancer/vocab/lexicon_loader.py
asr_enhancer/vocab/term_matcher.py
asr_enhancer-0.2.1.dist-info/licenses/LICENSE
asr_enhancer-0.2.1.dist-info/METADATA
asr_enhancer-0.2.1.dist-info/WHEEL
asr_enhancer-0.2.1.dist-info/entry_points.txt
asr_enhancer-0.2.1.dist-info/top_level.txt
asr_enhancer-0.2.1.dist-info/RECORD
