Metadata-Version: 2.4
Name: asr-enhancer
Version: 0.2.1
Summary: ASR Quality Enhancement Layer for Parakeet Multilingual ASR
Home-page: https://github.com/yourusername/asr-enhancer
Author: ASR Enhancement Team
License: MIT
Project-URL: Homepage, https://github.com/example/asr-enhancer
Project-URL: Documentation, https://github.com/example/asr-enhancer#readme
Project-URL: Repository, https://github.com/example/asr-enhancer
Keywords: asr,speech-recognition,nlp,transcription,enhancement
Classifier: Development Status :: 3 - Alpha
Classifier: Intended Audience :: Developers
Classifier: License :: OSI Approved :: MIT License
Classifier: Programming Language :: Python :: 3
Classifier: Programming Language :: Python :: 3.11
Classifier: Programming Language :: Python :: 3.12
Classifier: Topic :: Scientific/Engineering :: Artificial Intelligence
Classifier: Topic :: Multimedia :: Sound/Audio :: Speech
Requires-Python: >=3.11
License-File: LICENSE
Requires-Dist: fastapi>=0.104.0
Requires-Dist: uvicorn[standard]>=0.24.0
Requires-Dist: pydantic>=2.5.0
Requires-Dist: httpx>=0.25.0
Requires-Dist: click>=8.1.0
Requires-Dist: numpy>=1.24.0
Provides-Extra: audio
Requires-Dist: librosa>=0.10.0; extra == "audio"
Requires-Dist: soundfile>=0.12.0; extra == "audio"
Provides-Extra: whisper
Requires-Dist: openai-whisper>=20231117; extra == "whisper"
Provides-Extra: llm
Requires-Dist: openai>=1.3.0; extra == "llm"
Requires-Dist: anthropic>=0.7.0; extra == "llm"
Provides-Extra: ml
Requires-Dist: torch>=2.1.0; extra == "ml"
Requires-Dist: transformers>=4.35.0; extra == "ml"
Provides-Extra: dev
Requires-Dist: pytest>=7.4.0; extra == "dev"
Requires-Dist: pytest-asyncio>=0.21.0; extra == "dev"
Requires-Dist: pytest-cov>=4.1.0; extra == "dev"
Requires-Dist: black>=23.11.0; extra == "dev"
Requires-Dist: isort>=5.12.0; extra == "dev"
Requires-Dist: mypy>=1.7.0; extra == "dev"
Requires-Dist: ruff>=0.1.0; extra == "dev"
Provides-Extra: all
Requires-Dist: asr-enhancer[audio,dev,llm,ml,whisper]; extra == "all"
Dynamic: home-page
Dynamic: license-file
Dynamic: requires-python
